pydero/__init__.py
pydero/connection.py
pydero/contract.py
pydero/utils.py
pydero-1.0.0.dist-info/LICENSE
pydero-1.0.0.dist-info/METADATA
pydero-1.0.0.dist-info/WHEEL
pydero-1.0.0.dist-info/top_level.txt
pydero-1.0.0.dist-info/RECORD
