Metadata-Version: 2.1
Name: pydero
Version: 1.0.0
Summary: Python wrapper for interacting with the DERO blockdag
Home-page: https://github.com/jonlindg/pydero
Author: Jonathan Lindgren
Author-email: ejonathanlindgren@gmail.com
License: UNKNOWN
Platform: UNKNOWN
Classifier: Programming Language :: Python :: 3
Classifier: License :: OSI Approved :: MIT License
Classifier: Operating System :: OS Independent
Requires-Dist: requests
